{
  "$schema": "https://facets-cloud.github.io/facets-schemas/schemas/helm/helm.schema.json",
  "kind": "helm",
  "flavor": "default",
  "provided": false,
  "disabled": true,
  "metadata": {},
  "version": "0.1",
  "spec": {
    "helm": {
      "chart": "https://github.com/DataDog/helm-charts/releases/download/datadog-2.30.13/datadog-2.30.13.tgz",
      "namespace": "test-namespace",
      "wait": false
    },
    "values": {
      "datadog": {
        "service": {
          "annotations": {
            "key": "value"
          }
        }
      }
    }
  }
}